easydatastore/__init__.py
easydatastore/__init__.pyi
easydatastore/_meta.py
easydatastore/_meta.pyi
easydatastore/column.py
easydatastore/column.pyi
easydatastore/exceptions.py
easydatastore/exceptions.pyi
easydatastore/table.py
easydatastore/table.pyi
easydatastore-0.1.7.dist-info/LICENSE
easydatastore-0.1.7.dist-info/METADATA
easydatastore-0.1.7.dist-info/WHEEL
easydatastore-0.1.7.dist-info/RECORD
